1Cuatri_2º/EstrucComp/Primera_Practica_ALU/P1_final/compl1.v
module compl1 (output wire [3:0] Out, input wire [3:0] Inp, input wire cp1);

  assign Out = cp1 ? Inp : ~Inp;

endmodule

1Cuatri_2º/EstrucComp/Primera_Practica_ALU/P1_final/mux2_4.v
module mux2_4(output wire [3:0] Out, input  wire [3:0] A, input wire [3:0] B, input wire s);

  assign Out = s ? B : A;

endmodule

1Cuatri_2º/EstrucComp/Primera_Practica_ALU/P1_final/preprocess.v
module preprocess(output wire [3:0] AMod, output wire [3:0] BMod, input wire [3:0] A, input wire [3:0] B, input wire [2:0] Op);

  wire add1, op1_A, op2_B; //cpl
  wire [3:0] cable1, cable2;
  reg cpl;

  assign add1 = Op[0];
  assign op1_A = Op[2] | (Op[1] & ~Op[0]);
  assign op2_B = Op[2] | (Op[1] & ~Op[0]);
  assign cpl = (~Op[2] & ~Op[1]) & Op[0];

  always @(*) begin
  cpl = ((~Op[2] & ~Op[1]) & Op[0]);
  end

  mux2_4 mux1(cable1, 4'b0, 4'b1, add1);                   // add1
  mux2_4 mux2(AMod, cable1, A, op1_A);                     // op1_A
  mux2_4 mux3(cable2, A, B, op2_B);                        // op2_B
  compl1 C1(BMod, cable2, cpl);                            // C1

endmodule

1Cuatri_2º/EstrucComp/Primera_Practica_ALU/P1_final/mux4_1.v
// Multiplexor de 4 entradas y una salida de un bit
module mux4_1(output reg out, input wire a, b, c ,d, input wire [1:0] S);

  always @(a, b, c, d, S) begin
    case (S)
    2'b00: out = a;
    2'b01: out = b;
    2'b10: out = c;
    2'b11: out = d; 
    default: out = 1'bX; 
    endcase
  end

endmodule

1Cuatri_2º/EstrucComp/Primera_Practica_ALU/P1_final/cl.v
module cl(output wire out, input wire a, b, input wire [1:0] S);

  wire sA, sO, sX, sN;

  and and1(sA, a, b);
  or or1(sO, a, b);
  xor xor1(sX, a, b);
  not no1(sN, a);

  mux4_1 mux1(out, sA, sO, sX, sN, S);

endmodule

1Cuatri_2º/EstrucComp/Primera_Practica_ALU/P1_final/ul4.v
//Unidad lógica de 4 bits de forma estructural
module ul4(output wire [3:0] Out, input wire [3:0] A, input wire [3:0] B, input wire [1:0] S);

  cl cl1(Out[0], A[0], B[0], S);
  cl cl2(Out[1], A[1], B[1], S);
  cl cl3(Out[2], A[2], B[2], S);
  cl cl4(Out[3], A[3], B[3], S);

endmodule

1Cuatri_2º/EstrucComp/Primera Practica ALU/Obj 2/fa.v
module fa(output wire c_out, sum, input wire a, b, c_in);



endmodule

1Cuatri_2º/EstrucComp/Primera_Practica_ALU/P1_final/sum4_v1.v
module sum4_v1(output wire [3:0] S, output wire c_out, input wire [3:0] A, input wire [3:0] B, input wire c_in);

  wire c1, c2, c3;

  fa fa1(c1, S[0], A[0], B[0], c_in);
  fa fa2(c2, S[1], A[1], B[1], c1);
  fa fa3(c3, S[2], A[2], B[2], c2);
  fa fa4(c_out, S[3], A[3], B[3], c3);

endmodule

1Cuatri_2º/EstrucComp/Primera_Practica_ALU/P1_final/alu.v
module alu(output wire [3:0] R, output wire zero, carry, sign, input wire [3:0] A, B, input wire c_in, input wire [2:0] Op);

  wire [3:0] cable_Op1, cable_Op2, cable_sum, cable_ul4;

  sum4_v1 sumador(cable_sum, carry, cable_Op1, cable_Op2, c_in);
  ul4 u_logica(cable_ul4, cable_Op1, cable_Op2, Op[1:0]);
  mux2_4 mux(R, cable_sum, cable_ul4, Op[2]);

  assign zero = R ? 1'b0 : 1'b1;
  assign sign = R[3];

  // iverilog alu.v preprocess.v compl1.v sum4_v1.v fa.v u14.v cl.v mux4_1.v mux2_4.v
  // iverilog alu_tb.v alu.v prep.v compl1.v sum.v fa.v u14.v cl.v mux4_1.v mux2_4.v

endmodule

1Cuatri_2º/EstrucComp/Primera Practica ALU/alu_tb.v
// Testbench para modulo alu
`timescale 1 ns / 10 ps //Directiva que fija la unidad de tiempo de simulación y la precision de la unidad
module alu_tb;
//declaracion de señales
reg [2:0] t_Op;
reg t_cin;
reg [3:0] t_A, t_B; 
wire [3:0] t_R;
wire t_z, t_c, t_s;
integer errores;

// error de cualquier tipo, de resultado, de linea zero, de signo y carry
reg error, error_R, error_z, error_s, error_c; 

//instancia del modulo a testear
alu mat(t_R, t_z, t_c, t_s, t_A, t_B, t_cin, t_Op);


initial
begin
	$dumpfile("alu.vcd");
	$dumpvars;

	errores = 0;
	
	t_Op = 3'b000;
	repeat(8)
	begin
		t_cin = 1'b0;
		repeat(2)
		begin
			t_A = 4'b0;
			repeat(16) 
			begin
				t_B = 4'b0;
				repeat(16) 
				begin
					#0.01 check;
					#9.99;
					t_B = t_B + 1;
				end
				t_A = t_A + 1;
			end
			t_cin = t_cin + 1;
		end
		t_Op = t_Op + 1;
	end
	$display("Encontradas %d operaciones erroneas", errores);
  	//fin simulacion
  	$finish;
end

// Tarea para hacer la comprobación automática de resultados
task check;
reg [4:0] expected_R;
reg expected_z, expected_c, expected_s;

begin
	$write("tiempo=%0d A=%b B=%b c_in=%b OP=%b R=%b, Z=%b, C=%b, S=%b.", $time, t_A, t_B, t_cin, t_Op, t_R, t_z, t_c, t_s);
	case (t_Op)	
		3'b000: expected_R = t_A + t_B + t_cin;
		3'b001: expected_R = t_A + 1 + t_cin;
		3'b010: expected_R = (t_A ^4'b1111) + 4'b0001 + t_cin;
		3'b011: expected_R = (t_B ^4'b1111) + 4'b0001 + t_cin;
		3'b100: expected_R = t_A & t_B;
		3'b101: expected_R = t_A | t_B;
		3'b110: expected_R = t_A ^ t_B;
		3'b111: expected_R[3:0] = ~t_A;
		default: $display("ERROR. Valor no esperado para t_Op: %b", t_Op);
	endcase
	if (t_Op[2]) // Si la operación es lógica
	begin
		expected_c = 1'b0;
		expected_s = expected_R[3];
		error_s = 0;
	 	error_c = 0;
	end
	else
	begin
		expected_c = expected_R[4];
		expected_s = expected_R[3];
		error_s = (expected_s !== t_s);
	 	error_c = (expected_c !== t_c);
	end

	expected_z = ~| expected_R[3:0];
	// generacion señales error generales para toda la ALU
	error_R = (expected_R[3:0] !== t_R); 
	error_z = (expected_z !== t_z);
	error = error_R | error_z | error_s | error_c;
	if (error)
	begin
		errores = errores + 1;
		$display(" ---- ERROR");
		if (error_R)
			$display("\tResultado esperado %b, obtenido %b", expected_R[3:0], t_R);
		if (error_z)
			$display("\tFlag de cero esperado %b, obtenido %b", expected_z, t_z);
		if (error_s)
			$display("\tFlag de signo esperado %b, obtenido %b", expected_s, t_s);
		if (error_c)
			$display("\tFlag de acarreo esperado %b, obtenido %b", expected_c, t_c);
	end
	else
		$display(" ---- OK");
end
endtask
endmodule

1Cuatri_2º/EstrucComp/Primera_Practica_ALU/P1_final/alu.vcd
$date
	Thu Oct  2 18:32:41 2025
$end
$version
	Icarus Verilog
$end
$timescale
	10ps
$end
$scope module alu_tb $end
$var wire 1 ! t_z $end
$var wire 1 " t_s $end
$var wire 1 # t_c $end
$var wire 4 $ t_R [3:0] $end
$var reg 1 % error $end
$var reg 1 & error_R $end
$var reg 1 ' error_c $end
$var reg 1 ( error_s $end
$var reg 1 ) error_z $end
$var reg 4 * t_A [3:0] $end
$var reg 4 + t_B [3:0] $end
$var reg 3 , t_Op [2:0] $end
$var reg 1 - t_cin $end
$var integer 32 . errores [31:0] $end
$scope module mat $end
$var wire 4 / A [3:0] $end
$var wire 4 0 B [3:0] $end
$var wire 3 1 Op [2:0] $end
$var wire 1 - c_in $end
$var wire 4 2 cable_Op1 [3:0] $end
$var wire 4 3 cable_Op2 [3:0] $end
$var wire 1 ! zero $end
$var wire 1 " sign $end
$var wire 1 # carry $end
$var wire 4 4 cable_ul4 [3:0] $end
$var wire 4 5 cable_sum [3:0] $end
$var wire 4 6 R [3:0] $end
$scope module mux $end
$var wire 1 7 s $end
$var wire 4 8 Out [3:0] $end
$var wire 4 9 B [3:0] $end
$var wire 4 : A [3:0] $end
$upscope $end
$scope module sumador $end
$var wire 4 ; A [3:0] $end
$var wire 4 < B [3:0] $end
$var wire 1 - c_in $end
$var wire 1 # c_out $end
$var wire 1 = c3 $end
$var wire 1 > c2 $end
$var wire 1 ? c1 $end
$var wire 4 @ S [3:0] $end
$scope module fa1 $end
$var wire 1 A a $end
$var wire 1 B b $end
$var wire 1 - c_in $end
$var wire 1 C sum $end
$var wire 1 ? c_out $end
$upscope $end
$scope module fa2 $end
$var wire 1 D a $end
$var wire 1 E b $end
$var wire 1 ? c_in $end
$var wire 1 F sum $end
$var wire 1 > c_out $end
$upscope $end
$scope module fa3 $end
$var wire 1 G a $end
$var wire 1 H b $end
$var wire 1 > c_in $end
$var wire 1 I sum $end
$var wire 1 = c_out $end
$upscope $end
$scope module fa4 $end
$var wire 1 J a $end
$var wire 1 K b $end
$var wire 1 = c_in $end
$var wire 1 L sum $end
$var wire 1 # c_out $end
$upscope $end
$upscope $end
$scope module u_logica $end
$var wire 4 M A [3:0] $end
$var wire 4 N B [3:0] $end
$var wire 2 O S [1:0] $end
$var wire 4 P Out [3:0] $end
$scope module cl1 $end
$var wire 2 Q S [1:0] $end
$var wire 1 R a $end
$var wire 1 S b $end
$var wire 1 T sA $end
$var wire 1 U sN $end
$var wire 1 V sO $end
$var wire 1 W sX $end
$var wire 1 X out $end
$scope module mux1 $end
$var wire 2 Y S [1:0] $end
$var wire 1 T a $end
$var wire 1 V b $end
$var wire 1 W c $end
$var wire 1 U d $end
$var reg 1 X out $end
$upscope $end
$upscope $end
$scope module cl2 $end
$var wire 2 Z S [1:0] $end
$var wire 1 [ a $end
$var wire 1 \ b $end
$var wire 1 ] sA $end
$var wire 1 ^ sN $end
$var wire 1 _ sO $end
$var wire 1 ` sX $end
$var wire 1 a out $end
$scope module mux1 $end
$var wire 2 b S [1:0] $end
$var wire 1 ] a $end
$var wire 1 _ b $end
$var wire 1 ` c $end
$var wire 1 ^ d $end
$var reg 1 a out $end
$upscope $end
$upscope $end
$scope module cl3 $end
$var wire 2 c S [1:0] $end
$var wire 1 d a $end
$var wire 1 e b $end
$var wire 1 f sA $end
$var wire 1 g sN $end
$var wire 1 h sO $end
$var wire 1 i sX $end
$var wire 1 j out $end
$scope module mux1 $end
$var wire 2 k S [1:0] $end
$var wire 1 f a $end
$var wire 1 h b $end
$var wire 1 i c $end
$var wire 1 g d $end
$var reg 1 j out $end
$upscope $end
$upscope $end
$scope module cl4 $end
$var wire 2 l S [1:0] $end
$var wire 1 m a $end
$var wire 1 n b $end
$var wire 1 o sA $end
$var wire 1 p sN $end
$var wire 1 q sO $end
$var wire 1 r sX $end
$var wire 1 s out $end
$scope module mux1 $end
$var wire 2 t S [1:0] $end
$var wire 1 o a $end
$var wire 1 q b $end
$var wire 1 r c $end
$var wire 1 p d $end
$var reg 1 s out $end
$upscope $end
$upscope $end
$upscope $end
$upscope $end
$scope task check $end
$var reg 5 u expected_R [4:0] $end
$var reg 1 v expected_c $end
$var reg 1 w expected_s $end
$var reg 1 x expected_z $end
$upscope $end
$upscope $end
$scope module preprocess $end
$var wire 4 y A [3:0] $end
$var wire 4 z B [3:0] $end
$var wire 3 { Op [2:0] $end
$var wire 1 | cpl $end
$var wire 1 } op1_A $end
$var wire 1 ~ op2_B $end
$var wire 4 !" cable2 [3:0] $end
$var wire 4 "" cable1 [3:0] $end
$var wire 1 #" add1 $end
$var wire 4 $" BMod [3:0] $end
$var wire 4 %" AMod [3:0] $end
$scope module C1 $end
$var wire 1 | cp1 $end
$var wire 4 &" Out [3:0] $end
$var wire 4 '" Inp [3:0] $end
$upscope $end
$scope module mux1 $end
$var wire 4 (" A [3:0] $end
$var wire 4 )" B [3:0] $end
$var wire 1 #" s $end
$var wire 4 *" Out [3:0] $end
$upscope $end
$scope module mux2 $end
$var wire 4 +" A [3:0] $end
$var wire 4 ," B [3:0] $end
$var wire 1 } s $end
$var wire 4 -" Out [3:0] $end
$upscope $end
$scope module mux3 $end
$var wire 4 ." A [3:0] $end
$var wire 4 /" B [3:0] $end
$var wire 1 ~ s $end
$var wire 4 0" Out [3:0] $end
$upscope $end
$upscope $end
$enddefinitions $end
$comment Show the parameter values. $end
$dumpall
$end
#0
$dumpvars
bz 0"
bz /"
bz ."
bx -"
bz ,"
b0x +"
b0x *"
b1 )"
b0 ("
bz '"
bz &"
bx %"
bz $"
z#"
b0x ""
bz !"
x~
x}
x|
bz {
bz z
bz y
xx
xw
xv
bx u
b0 t
xs
xr
xq
zp
xo
zn
zm
b0 l
b0 k
xj
xi
xh
zg
xf
ze
zd
b0 c
b0 b
xa
x`
x_
z^
x]
z\
z[
b0 Z
b0 Y
xX
xW
xV
zU
xT
zS
zR
b0 Q
bx P
b0 O
bz N
bz M
xL
zK
zJ
xI
zH
zG
xF
zE
zD
xC
zB
zA
bx @
x?
x>
x=
bz <
bz ;
bx :
bx 9
bx 8
07
bx 6
bx 5
bx 4
bz 3
bz 2
b0 1
b0 0
b0 /
b0 .
0-
b0 ,
b0 +
b0 *
x)
x(
x'
x&
x%
bx $
x#
x"
x!
$end
#1
b1 .
1%
1)
1&
1x
1'
1(
0w
0v
b0 u
#1000
b1 +
b1 0
#1001
b10 .
0x
b1 u
#2000
b10 +
b10 0
#2001
b11 .
b10 u
#3000
b11 +
b11 0
#3001
b100 .
b11 u
#4000
b100 +
b100 0
#4001
b101 .
b100 u
#5000
b101 +
b101 0
#5001
b110 .
b101 u
#6000
b110 +
b110 0
#6001
b111 .
b110 u
#7000
b111 +
b111 0
#7001
b1000 .
b111 u
#8000
b1000 +
b1000 0
#8001
b1001 .
1w
b1000 u
#9000
b1001 +
b1001 0
#9001
b1010 .
b1001 u
#10000
b1010 +
b1010 0
#10001
b1011 .
b1010 u
#11000
b1011 +
b1011 0
#11001
b1100 .
b1011 u
#12000
b1100 +
b1100 0
#12001
b1101 .
b1100 u
#13000
b1101 +
b1101 0
#13001
b1110 .
b1101 u
#14000
b1110 +
b1110 0
#14001
b1111 .
b1110 u
#15000
b1111 +
b1111 0
#15001
b10000 .
b1111 u
#16000
b1 *
b1 /
b0 +
b0 0
#16001
b10001 .
0w
b1 u
#17000
b1 +
b1 0
#17001
b10010 .
b10 u
#18000
b10 +
b10 0
#18001
b10011 .
b11 u
#19000
b11 +
b11 0
#19001
b10100 .
b100 u
#20000
b100 +
b100 0
#20001
b10101 .
b101 u
#21000
b101 +
b101 0
#21001
b10110 .
b110 u
#22000
b110 +
b110 0
#22001
b10111 .
b111 u
#23000
b111 +
b111 0
#23001
b11000 .
1w
b1000 u
#24000
b1000 +
b1000 0
#24001
b11001 .
b1001 u
#25000
b1001 +
b1001 0
#25001
b11010 .
b1010 u
#26000
b1010 +
b1010 0
#26001
b11011 .
b1011 u
#27000
b1011 +
b1011 0
#27001
b11100 .
b1100 u
#28000
b1100 +
b1100 0
#28001
b11101 .
b1101 u
#29000
b1101 +
b1101 0
#29001
b11110 .
b1110 u
#30000
b1110 +
b1110 0
#30001
b11111 .
b1111 u
#31000
b1111 +
b1111 0
#31001
b100000 .
1x
0w
1v
b10000 u
#32000
b10 *
b10 /
b0 +
b0 0
#32001
b100001 .
0x
0v
b10 u
#33000
b1 +
b1 0
#33001
b100010 .
b11 u
#34000
b10 +
b10 0
#34001
b100011 .
b100 u
#35000
b11 +
b11 0
#35001
b100100 .
b101 u
#36000
b100 +
b100 0
#36001
b100101 .
b110 u
#37000
b101 +
b101 0
#37001
b100110 .
b111 u
#38000
b110 +
b110 0
#38001
b100111 .
1w
b1000 u
#39000
b111 +
b111 0
#39001
b101000 .
b1001 u
#40000
b1000 +
b1000 0
#40001
b101001 .
b1010 u
#41000
b1001 +
b1001 0
#41001
b101010 .
b1011 u
#42000
b1010 +
b1010 0
#42001
b101011 .
b1100 u
#43000
b1011 +
b1011 0
#43001
b101100 .
b1101 u
#44000
b1100 +
b1100 0
#44001
b101101 .
b1110 u
#45000
b1101 +
b1101 0
#45001
b101110 .
b1111 u
#46000
b1110 +
b1110 0
#46001
b101111 .
1x
0w
1v
b10000 u
#47000
b1111 +
b1111 0
#47001
b110000 .
0x
b10001 u
#48000
b11 *
b11 /
b0 +
b0 0
#48001
b110001 .
0v
b11 u
#49000
b1 +
b1 0
#49001
b110010 .
b100 u
#50000
b10 +
b10 0
#50001
b110011 .
b101 u
#51000
b11 +
b11 0
#51001
b110100 .
b110 u
#52000
b100 +
b100 0
#52001
b110101 .
b111 u
#53000
b101 +
b101 0
#53001
b110110 .
1w
b1000 u
#54000
b110 +
b110 0
#54001
b110111 .
b1001 u
#55000
b111 +
b111 0
#55001
b111000 .
b1010 u
#56000
b1000 +
b1000 0
#56001
b111001 .
b1011 u
#57000
b1001 +
b1001 0
#57001
b111010 .
b1100 u
#58000
b1010 +
b1010 0
#58001
b111011 .
b1101 u
#59000
b1011 +
b1011 0
#59001
b111100 .
b1110 u
#60000
b1100 +
b1100 0
#60001
b111101 .
b1111 u
#61000
b1101 +
b1101 0
#61001
b111110 .
1x
0w
1v
b10000 u
#62000
b1110 +
b1110 0
#62001
b111111 .
0x
b10001 u
#63000
b1111 +
b1111 0
#63001
b1000000 .
b10010 u
#64000
b100 *
b100 /
b0 +
b0 0
#64001
b1000001 .
0v
b100 u
#65000
b1 +
b1 0
#65001
b1000010 .
b101 u
#66000
b10 +
b10 0
#66001
b1000011 .
b110 u
#67000
b11 +
b11 0
#67001
b1000100 .
b111 u
#68000
b100 +
b100 0
#68001
b1000101 .
1w
b1000 u
#69000
b101 +
b101 0
#69001
b1000110 .
b1001 u
#70000
b110 +
b110 0
#70001
b1000111 .
b1010 u
#71000
b111 +
b111 0
#71001
b1001000 .
b1011 u
#72000
b1000 +
b1000 0
#72001
b1001001 .
b1100 u
#73000
b1001 +
b1001 0
#73001
b1001010 .
b1101 u
#74000
b1010 +
b1010 0
#74001
b1001011 .
b1110 u
#75000
b1011 +
b1011 0
#75001
b1001100 .
b1111 u
#76000
b1100 +
b1100 0
#76001
b1001101 .
1x
0w
1v
b10000 u
#77000
b1101 +
b1101 0
#77001
b1001110 .
0x
b10001 u
#78000
b1110 +
b1110 0
#78001
b1001111 .
b10010 u
#79000
b1111 +
b1111 0
#79001
b1010000 .
b10011 u
#80000
b101 *
b101 /
b0 +
b0 0
#80001
b1010001 .
0v
b101 u
#81000
b1 +
b1 0
#81001
b1010010 .
b110 u
#82000
b10 +
b10 0
#82001
b1010011 .
b111 u
#83000
b11 +
b11 0
#83001
b1010100 .
1w
b1000 u
#84000
b100 +
b100 0
#84001
b1010101 .
b1001 u
#85000
b101 +
b101 0
#85001
b1010110 .
b1010 u
#86000
b110 +
b110 0
#86001
b1010111 .
b1011 u
#87000
b111 +
b111 0
#87001
b1011000 .
b1100 u
#88000
b1000 +
b1000 0
#88001
b1011001 .
b1101 u
#89000
b1001 +
b1001 0
#89001
b1011010 .
b1110 u
#90000
b1010 +
b1010 0
#90001
b1011011 .
b1111 u
#91000
b1011 +
b1011 0
#91001
b1011100 .
1x
0w
1v
b10000 u
#92000
b1100 +
b1100 0
#92001
b1011101 .
0x
b10001 u
#93000
b1101 +
b1101 0
#93001
b1011110 .
b10010 u
#94000
b1110 +
b1110 0
#94001
b1011111 .
b10011 u
#95000
b1111 +
b1111 0
#95001
b1100000 .
b10100 u
#96000
b110 *
b110 /
b0 +
b0 0
#96001
b1100001 .
0v
b110 u
#97000
b1 +
b1 0
#97001
b1100010 .
b111 u
#98000
b10 +
b10 0
#98001
b1100011 .
1w
b1000 u
#99000
b11 +
b11 0
#99001
b1100100 .
b1001 u
#100000
b100 +
b100 0
#100001
b1100101 .
b1010 u
#101000
b101 +
b101 0
#101001
b1100110 .
b1011 u
#102000
b110 +
b110 0
#102001
b1100111 .
b1100 u
#103000
b111 +
b111 0
#103001
b1101000 .
b1101 u
#104000
b1000 +
b1000 0
#104001
b1101001 .
b1110 u
#105000
b1001 +
b1001 0
#105001
b1101010 .
b1111 u
#106000
b1010 +
b1010 0
#106001
b1101011 .
1x
0w
1v
b10000 u
#107000
b1011 +
b1011 0
#107001
b1101100 .
0x
b10001 u
#108000
b1100 +
b1100 0
#108001
b1101101 .
b10010 u
#109000
b1101 +
b1101 0
#109001
b1101110 .
b10011 u
#110000
b1110 +
b1110 0
#110001
b1101111 .
b10100 u
#111000
b1111 +
b1111 0
#111001
b1110000 .
b10101 u
#112000
b111 *
b111 /
b0 +
b0 0
#112001
b1110001 .
0v
b111 u
#113000
b1 +
b1 0
#113001
b1110010 .
1w
b1000 u
#114000
b10 +
b10 0
#114001
b1110011 .
b1001 u
#115000
b11 +
b11 0
#115001
b1110100 .
b1010 u
#116000
b100 +
b100 0
#116001
b1110101 .
b1011 u
#117000
b101 +
b101 0
#117001
b1110110 .
b1100 u
#118000
b110 +
b110 0
#118001
b1110111 .
b1101 u
#119000
b111 +
b111 0
#119001
b1111000 .
b1110 u
#120000
b1000 +
b1000 0
#120001
b1111001 .
b1111 u
#121000
b1001 +
b1001 0
#121001
b1111010 .
1x
0w
1v
b10000 u
#122000
b1010 +
b1010 0
#122001
b1111011 .
0x
b10001 u
#123000
b1011 +
b1011 0
#123001
b1111100 .
b10010 u
#124000
b1100 +
b1100 0
#124001
b1111101 .
b10011 u
#125000
b1101 +
b1101 0
#125001
b1111110 .
b10100 u
#126000
b1110 +
b1110 0
#126001
b1111111 .
b10101 u
#127000
b1111 +
b1111 0
#127001
b10000000 .
b10110 u
#128000
b1000 *
b1000 /
b0 +
b0 0
#128001
b10000001 .
1w
0v
b1000 u
#129000
b1 +
b1 0
#129001
b10000010 .
b1001 u
#130000
b10 +
b10 0
#130001
b10000011 .
b1010 u
#131000
b11 +
b11 0
#131001
b10000100 .
b1011 u
#132000
b100 +
b100 0
#132001
b10000101 .
b1100 u
#133000
b101 +
b101 0
#133001
b10000110 .
b1101 u
#134000
b110 +
b110 0
#134001
b10000111 .
b1110 u
#135000
b111 +
b111 0
#135001
b10001000 .
b1111 u
#136000
b1000 +
b1000 0
#136001
b10001001 .
1x
0w
1v
b10000 u
#137000
b1001 +
b1001 0
#137001
b10001010 .
0x
b10001 u
#138000
b1010 +
b1010 0
#138001
b10001011 .
b10010 u
#139000
b1011 +
b1011 0
#139001
b10001100 .
b10011 u
#140000
b1100 +
b1100 0
#140001
b10001101 .
b10100 u
#141000
b1101 +
b1101 0
#141001
b10001110 .
b10101 u
#142000
b1110 +
b1110 0
#142001
b10001111 .
b10110 u
#143000
b1111 +
b1111 0
#143001
b10010000 .
b10111 u
#144000
b1001 *
b1001 /
b0 +
b0 0
#144001
b10010001 .
1w
0v
b1001 u
#145000
b1 +
b1 0
#145001
b10010010 .
b1010 u
#146000
b10 +
b10 0
#146001
b10010011 .
b1011 u
#147000
b11 +
b11 0
#147001
b10010100 .
b1100 u
#148000
b100 +
b100 0
#148001
b10010101 .
b1101 u
#149000
b101 +
b101 0
#149001
b10010110 .
b1110 u
#150000
b110 +
b110 0
#150001
b10010111 .
b1111 u
#151000
b111 +
b111 0
#151001
b10011000 .
1x
0w
1v
b10000 u
#152000
b1000 +
b1000 0
#152001
b10011001 .
0x
b10001 u
#153000
b1001 +
b1001 0
#153001
b10011010 .
b10010 u
#154000
b1010 +
b1010 0
#154001
b10011011 .
b10011 u
#155000
b1011 +
b1011 0
#155001
b10011100 .
b10100 u
#156000
b1100 +
b1100 0
#156001
b10011101 .
b10101 u
#157000
b1101 +
b1101 0
#157001
b10011110 .
b10110 u
#158000
b1110 +
b1110 0
#158001
b10011111 .
b10111 u
#159000
b1111 +
b1111 0
#159001
b10100000 .
1w
b11000 u
#160000
b1010 *
b1010 /
b0 +
b0 0
#160001
b10100001 .
0v
b1010 u
#161000
b1 +
b1 0
#161001
b10100010 .
b1011 u
#162000
b10 +
b10 0
#162001
b10100011 .
b1100 u
#163000
b11 +
b11 0
#163001
b10100100 .
b1101 u
#164000
b100 +
b100 0
#164001
b10100101 .
b1110 u
#165000
b101 +
b101 0
#165001
b10100110 .
b1111 u
#166000
b110 +
b110 0
#166001
b10100111 .
1x
0w
1v
b10000 u
#167000
b111 +
b111 0
#167001
b10101000 .
0x
b10001 u
#168000
b1000 +
b1000 0
#168001
b10101001 .
b10010 u
#169000
b1001 +
b1001 0
#169001
b10101010 .
b10011 u
#170000
b1010 +
b1010 0
#170001
b10101011 .
b10100 u
#171000
b1011 +
b1011 0
#171001
b10101100 .
b10101 u
#172000
b1100 +
b1100 0
#172001
b10101101 .
b10110 u
#173000
b1101 +
b1101 0
#173001
b10101110 .
b10111 u
#174000
b1110 +
b1110 0
#174001
b10101111 .
1w
b11000 u
#175000
b1111 +
b1111 0
#175001
b10110000 .
b11001 u
#176000
b1011 *
b1011 /
b0 +
b0 0
#176001
b10110001 .
0v
b1011 u
#177000
b1 +
b1 0
#177001
b10110010 .
b1100 u
#178000
b10 +
b10 0
#178001
b10110011 .
b1101 u
#179000
b11 +
b11 0
#179001
b10110100 .
b1110 u
#180000
b100 +
b100 0
#180001
b10110101 .
b1111 u
#181000
b101 +
b101 0
#181001
b10110110 .
1x
0w
1v
b10000 u
#182000
b110 +
b110 0
#182001
b10110111 .
0x
b10001 u
#183000
b111 +
b111 0
#183001
b10111000 .
b10010 u
#184000
b1000 +
b1000 0
#184001
b10111001 .
b10011 u
#185000
b1001 +
b1001 0
#185001
b10111010 .
b10100 u
#186000
b1010 +
b1010 0
#186001
b10111011 .
b10101 u
#187000
b1011 +
b1011 0
#187001
b10111100 .
b10110 u
#188000
b1100 +
b1100 0
#188001
b10111101 .
b10111 u
#189000
b1101 +
b1101 0
#189001
b10111110 .
1w
b11000 u
#190000
b1110 +
b1110 0
#190001
b10111111 .
b11001 u
#191000
b1111 +
b1111 0
#191001
b11000000 .
b11010 u
#192000
b1100 *
b1100 /
b0 +
b0 0
#192001
b11000001 .
0v
b1100 u
#193000
b1 +
b1 0
#193001
b11000010 .
b1101 u
#194000
b10 +
b10 0
#194001
b11000011 .
b1110 u
#195000
b11 +
b11 0
#195001
b11000100 .
b1111 u
#196000
b100 +
b100 0
#196001
b11000101 .
1x
0w
1v
b10000 u
#197000
b101 +
b101 0
#197001
b11000110 .
0x
b10001 u
#198000
b110 +
b110 0
#198001
b11000111 .
b10010 u
#199000
b111 +
b111 0
#199001
b11001000 .
b10011 u
#200000
b1000 +
b1000 0
#200001
b11001001 .
b10100 u
#201000
b1001 +
b1001 0
#201001
b11001010 .
b10101 u
#202000
b1010 +
b1010 0
#202001
b11001011 .
b10110 u
#203000
b1011 +
b1011 0
#203001
b11001100 .
b10111 u
#204000
b1100 +
b1100 0
#204001
b11001101 .
1w
b11000 u
#205000
b1101 +
b1101 0
#205001
b11001110 .
b11001 u
#206000
b1110 +
b1110 0
#206001
b11001111 .
b11010 u
#207000
b1111 +
b1111 0
#207001
b11010000 .
b11011 u
#208000
b1101 *
b1101 /
b0 +
b0 0
#208001
b11010001 .
0v
b1101 u
#209000
b1 +
b1 0
#209001
b11010010 .
b1110 u
#210000
b10 +
b10 0
#210001
b11010011 .
b1111 u
#211000
b11 +
b11 0
#211001
b11010100 .
1x
0w
1v
b10000 u
#212000
b100 +
b100 0
#212001
b11010101 .
0x
b10001 u
#213000
b101 +
b101 0
#213001
b11010110 .
b10010 u
#214000
b110 +
b110 0
#214001
b11010111 .
b10011 u
#215000
b111 +
b111 0
#215001
b11011000 .
b10100 u
#216000
b1000 +
b1000 0
#216001
b11011001 .
b10101 u
#217000
b1001 +
b1001 0
#217001
b11011010 .
b10110 u
#218000
b1010 +
b1010 0
#218001
b11011011 .
b10111 u
#219000
b1011 +
b1011 0
#219001
b11011100 .
1w
b11000 u
#220000
b1100 +
b1100 0
#220001
b11011101 .
b11001 u
#221000
b1101 +
b1101 0
#221001
b11011110 .
b11010 u
#222000
b1110 +
b1110 0
#222001
b11011111 .
b11011 u
#223000
b1111 +
b1111 0
#223001
b11100000 .
b11100 u
#224000
b1110 *
b1110 /
b0 +
b0 0
#224001
b11100001 .
0v
b1110 u
#225000
b1 +
b1 0
#225001
b11100010 .
b1111 u
#226000
b10 +
b10 0
#226001
b11100011 .
1x
0w
1v
b10000 u
#227000
b11 +
b11 0
#227001
b11100100 .
0x
b10001 u
#228000
b100 +
b100 0
#228001
b11100101 .
b10010 u
#229000
b101 +
b101 0
#229001
b11100110 .
b10011 u
#230000
b110 +
b110 0
#230001
b11100111 .
b10100 u
#231000
b111 +
b111 0
#231001
b11101000 .
b10101 u
#232000
b1000 +
b1000 0
#232001
b11101001 .
b10110 u
#233000
b1001 +
b1001 0
#233001
b11101010 .
b10111 u
#234000
b1010 +
b1010 0
#234001
b11101011 .
1w
b11000 u
#235000
b1011 +
b1011 0
#235001
b11101100 .
b11001 u
#236000
b1100 +
b1100 0
#236001
b11101101 .
b11010 u
#237000
b1101 +
b1101 0
#237001
b11101110 .
b11011 u
#238000
b1110 +
b1110 0
#238001
b11101111 .
b11100 u
#239000
b1111 +
b1111 0
#239001
b11110000 .
b11101 u
#240000
b1111 *
b1111 /
b0 +
b0 0
#240001
b11110001 .
0v
b1111 u
#241000
b1 +
b1 0
#241001
b11110010 .
1x
0w
1v
b10000 u
#242000
b10 +
b10 0
#242001
b11110011 .
0x
b10001 u
#243000
b11 +
b11 0
#243001
b11110100 .
b10010 u
#244000
b100 +
b100 0
#244001
b11110101 .
b10011 u
#245000
b101 +
b101 0
#245001
b11110110 .
b10100 u
#246000
b110 +
b110 0
#246001
b11110111 .
b10101 u
#247000
b111 +
b111 0
#247001
b11111000 .
b10110 u
#248000
b1000 +
b1000 0
#248001
b11111001 .
b10111 u
#249000
b1001 +
b1001 0
#249001
b11111010 .
1w
b11000 u
#250000
b1010 +
b1010 0
#250001
b11111011 .
b11001 u
#251000
b1011 +
b1011 0
#251001
b11111100 .
b11010 u
#252000
b1100 +
b1100 0
#252001
b11111101 .
b11011 u
#253000
b1101 +
b1101 0
