1Cuatri_2º/EstrucComp/Primera Practica ALU/Obj 2/fa.v
module fa(output wire c_out, sum, input wire a, b, c_in);



endmodule

1Cuatri_2º/EstrucComp/Primera_Practica_ALU/P1_final/mux2_4.v
module mux2_4(output wire /*reg*/ [3:0] Out, input  wire [3:0] A, input wire [3:0] B, input wire s);

  assign Out = s ? B : A;

/* De forma conductual
  always @(*) begin
    case(s)
      1'b0 : Out = A;
      1'b1 : Out = B;
      default : Out = 1'bX;
    endcase
  end
*/

endmodule

1Cuatri_2º/EstrucComp/Primera_Practica_ALU/P1_final/mux4_1.v
// Multiplexor de 4 entradas y una salida de un bit
module mux4_1(output reg out, input wire a, b, c ,d, input wire [1:0] S);

  always @(a, b, c, d, S) begin
    case (S)
      2'b00: out = a;
      2'b01: out = b;
      2'b10: out = c;
      2'b11: out = d; 
      default: out = 1'bX; 
    endcase
  end

endmodule

1Cuatri_2º/EstrucComp/Primera_Practica_ALU/P1_final/cl.v
module cl(output wire out, input wire a, b, input wire [1:0] S);

  wire sA, sO, sX, sN;

  and and1(sA, a, b);
  or or1(sO, a, b);
  xor xor1(sX, a, b);
  not no1(sN, a);

  mux4_1 mux1(out, sA,  sO, sX, sN, S);

endmodule

1Cuatri_2º/EstrucComp/Primera_Practica_ALU/P1_final/ul4.v
//Unidad lógica de 4 bits de forma estructural
module ul4(output wire [3:0] Out, input wire [3:0] A, input wire [3:0] B, input wire [1:0] S);

  cl cl1(Out[0], A[0], B[0], S);
  cl cl2(Out[1], A[1], B[1], S);
  cl cl3(Out[2], A[2], B[2], S);
  cl cl4(Out[3], A[3], B[3], S);

endmodule

1Cuatri_2º/EstrucComp/Primera Practica ALU/Obj 2/sum4_v1.v
module sum4_v1(output wire [3:0] S, output wire c_out, input wire [3:0] A, input wire [3:0] B, input wire c_in);

  fa fa1(.sum(S[0]), .c_out[c1], .a(A[0]), .b(B[0]), .c_in(c_in));
  fa fa2(.sum(S[1]), .c_out[c2], .a(A[1]), .b(B[1]), .c_in(c1));
  fa fa3(.sum(S[2]), .c_out[c3], .a(A[2]), .b(B[2]), .c_in(c2));
  fa fa4(.sum(S[3]), .c_out[c_out], .a(A[3]), .b(B[3]), .c_in(c3));
  
endmodule

1Cuatri_2º/EstrucComp/Primera_Practica_ALU/P1_final/compl1.v
module compl1 (output wire [3:0] Out, input wire [3:0] Inp, input wire cp1);

  assign Out = cp1 ? ~Inp : Inp;

endmodule

1Cuatri_2º/EstrucComp/Primera_Practica_ALU/P1_final/preprocess.v
module preprocess(output wire [3:0] AMod, output wire [3:0] BMod, input wire [3:0] A, input wire [3:0] B, input wire [2:0] Op);

  wire add1, op1_A, op2_B, cp1;
  wire [3:0] cable1, cable2;
  //reg cpl;

  assign add1 = 1'b1;
  assign op1_A = Op[2] |(~Op[1] & ~Op[0]);
  assign op2_B = Op[2] | (~Op[1] & ~Op[0]) | (Op[1] & Op[0]);
  assign cp1 = ~Op[2] & Op[1];

  /*always @(*) begin
  cp1 = ~Op[2] & Op[1];
  end
  */

  mux2_4 mux1(cable1, 4'b0, 4'b1, add1);                   // add1
  mux2_4 mux2(AMod, cable1, A, op1_A);                     // op1_A
  mux2_4 mux3(cable2, A, B, op2_B);                        // op2_B
  compl1 cpl(BMod, cable2, cp1);                           // Cpl

endmodule


/*

Operacion   Op2   Op1   Op0   Add1    Op1_A   Op2_B   Cpl
A+B+c_in    0     0     0     X       1       1       0
A+1+c_in    0     0     1     1       0       0       0
-A+c_in     0     1     0     1       0       0       1
-B+c_in     0     1     1     1       0       1       1
A and B     1     0     0     X       1       1       0
a or B      1     0     1     X       1       1       0
A xor B     1     1     0     X       1       1       0
Not A       1     1     1     X       X       1       X

1Cuatri_2º/EstrucComp/Primera_Practica_ALU/P1_final/alu.v
module alu(output wire [3:0] R, output wire zero, carry, sign, input wire [3:0] A, B, input wire c_in, input wire [2:0] Op);

  wire [3:0] cable_Op1, cable_Op2, cable_sum, cable_ul4;

  preprocess preprocesador(cable_Op1, cable_Op2, A, B, Op);
  sum4_v1 sumador(cable_sum, carry, cable_Op1, cable_Op2, c_in);
  ul4 u_logica(cable_ul4, cable_Op1, cable_Op2, Op[1:0]);
  mux2_4 mux(R, cable_sum, cable_ul4, Op[2]);
  

  assign zero = R ? 1'b0 : 1'b1;
  assign sign = R[3];

  // iverilog -o test_alu alu_tb.v compl1.v mux2_4.v preprocess.v sum4_v1.v ul4.v alu.v cl.v fa.v mux4_1.v
  // vvp test_alu
  // gtkwave alu.vcd

endmodule

1Cuatri_2º/EstrucComp/Primera Practica ALU/alu_tb.v
// Testbench para modulo alu
`timescale 1 ns / 10 ps //Directiva que fija la unidad de tiempo de simulación y la precision de la unidad
module alu_tb;
//declaracion de señales
reg [2:0] t_Op;
reg t_cin;
reg [3:0] t_A, t_B; 
wire [3:0] t_R;
wire t_z, t_c, t_s;
integer errores;

// error de cualquier tipo, de resultado, de linea zero, de signo y carry
reg error, error_R, error_z, error_s, error_c; 

//instancia del modulo a testear
alu mat(t_R, t_z, t_c, t_s, t_A, t_B, t_cin, t_Op);


initial
begin
	$dumpfile("alu.vcd");
	$dumpvars;

	errores = 0;
	
	t_Op = 3'b000;
	repeat(8)
	begin
		t_cin = 1'b0;
		repeat(2)
		begin
			t_A = 4'b0;
			repeat(16) 
			begin
				t_B = 4'b0;
				repeat(16) 
				begin
					#0.01 check;
					#9.99;
					t_B = t_B + 1;
				end
				t_A = t_A + 1;
			end
			t_cin = t_cin + 1;
		end
		t_Op = t_Op + 1;
	end
	$display("Encontradas %d operaciones erroneas", errores);
  	//fin simulacion
  	$finish;
end

// Tarea para hacer la comprobación automática de resultados
task check;
reg [4:0] expected_R;
reg expected_z, expected_c, expected_s;

begin
	$write("tiempo=%0d A=%b B=%b c_in=%b OP=%b R=%b, Z=%b, C=%b, S=%b.", $time, t_A, t_B, t_cin, t_Op, t_R, t_z, t_c, t_s);
	case (t_Op)	
		3'b000: expected_R = t_A + t_B + t_cin;
		3'b001: expected_R = t_A + 1 + t_cin;
		3'b010: expected_R = (t_A ^4'b1111) + 4'b0001 + t_cin;
		3'b011: expected_R = (t_B ^4'b1111) + 4'b0001 + t_cin;
		3'b100: expected_R = t_A & t_B;
		3'b101: expected_R = t_A | t_B;
		3'b110: expected_R = t_A ^ t_B;
		3'b111: expected_R[3:0] = ~t_A;
		default: $display("ERROR. Valor no esperado para t_Op: %b", t_Op);
	endcase
	if (t_Op[2]) // Si la operación es lógica
	begin
		expected_c = 1'b0;
		expected_s = expected_R[3];
		error_s = 0;
	 	error_c = 0;
	end
	else
	begin
		expected_c = expected_R[4];
		expected_s = expected_R[3];
		error_s = (expected_s !== t_s);
	 	error_c = (expected_c !== t_c);
	end

	expected_z = ~| expected_R[3:0];
	// generacion señales error generales para toda la ALU
	error_R = (expected_R[3:0] !== t_R); 
	error_z = (expected_z !== t_z);
	error = error_R | error_z | error_s | error_c;
	if (error)
	begin
		errores = errores + 1;
		$display(" ---- ERROR");
		if (error_R)
			$display("\tResultado esperado %b, obtenido %b", expected_R[3:0], t_R);
		if (error_z)
			$display("\tFlag de cero esperado %b, obtenido %b", expected_z, t_z);
		if (error_s)
			$display("\tFlag de signo esperado %b, obtenido %b", expected_s, t_s);
		if (error_c)
			$display("\tFlag de acarreo esperado %b, obtenido %b", expected_c, t_c);
	end
	else
		$display(" ---- OK");
end
endtask
endmodule

1Cuatri_2º/EstrucComp/Primera_Practica_ALU/P1_final/alu.vcd
$date
	Mon Oct 13 21:41:33 2025
$end
$version
	Icarus Verilog
$end
$timescale
	10ps
$end
$scope module alu_tb $end
$var wire 1 ! t_z $end
$var wire 1 " t_s $end
$var wire 1 # t_c $end
$var wire 4 $ t_R [3:0] $end
$var reg 1 % error $end
$var reg 1 & error_R $end
$var reg 1 ' error_c $end
$var reg 1 ( error_s $end
$var reg 1 ) error_z $end
$var reg 4 * t_A [3:0] $end
$var reg 4 + t_B [3:0] $end
$var reg 3 , t_Op [2:0] $end
$var reg 1 - t_cin $end
$var integer 32 . errores [31:0] $end
$scope module mat $end
$var wire 4 / A [3:0] $end
$var wire 4 0 B [3:0] $end
$var wire 3 1 Op [2:0] $end
$var wire 1 - c_in $end
$var wire 1 ! zero $end
$var wire 1 " sign $end
$var wire 1 # carry $end
$var wire 4 2 cable_ul4 [3:0] $end
$var wire 4 3 cable_sum [3:0] $end
$var wire 4 4 cable_Op2 [3:0] $end
$var wire 4 5 cable_Op1 [3:0] $end
$var wire 4 6 R [3:0] $end
$scope module mux $end
$var wire 1 7 s $end
$var wire 4 8 Out [3:0] $end
$var wire 4 9 B [3:0] $end
$var wire 4 : A [3:0] $end
$upscope $end
$scope module preprocesador $end
$var wire 4 ; A [3:0] $end
$var wire 4 < B [3:0] $end
$var wire 3 = Op [2:0] $end
$var wire 1 > add1 $end
$var wire 1 ? cp1 $end
$var wire 1 @ op1_A $end
$var wire 1 A op2_B $end
$var wire 4 B cable2 [3:0] $end
$var wire 4 C cable1 [3:0] $end
$var wire 4 D BMod [3:0] $end
$var wire 4 E AMod [3:0] $end
$scope module cpl $end
$var wire 1 ? cp1 $end
$var wire 4 F Out [3:0] $end
$var wire 4 G Inp [3:0] $end
$upscope $end
$scope module mux1 $end
$var wire 4 H A [3:0] $end
$var wire 4 I B [3:0] $end
$var wire 4 J Out [3:0] $end
$var wire 1 > s $end
$upscope $end
$scope module mux2 $end
$var wire 4 K A [3:0] $end
$var wire 4 L B [3:0] $end
$var wire 1 @ s $end
$var wire 4 M Out [3:0] $end
$upscope $end
$scope module mux3 $end
$var wire 4 N A [3:0] $end
$var wire 4 O B [3:0] $end
$var wire 1 A s $end
$var wire 4 P Out [3:0] $end
$upscope $end
$upscope $end
$scope module sumador $end
$var wire 4 Q A [3:0] $end
$var wire 4 R B [3:0] $end
$var wire 1 - c_in $end
$var wire 1 # c_out $end
$var wire 4 S S [3:0] $end
$upscope $end
$scope module u_logica $end
$var wire 4 T A [3:0] $end
$var wire 4 U B [3:0] $end
$var wire 2 V S [1:0] $end
$var wire 4 W Out [3:0] $end
$scope module cl1 $end
$var wire 2 X S [1:0] $end
$var wire 1 Y a $end
$var wire 1 Z b $end
$var wire 1 [ sA $end
$var wire 1 \ sN $end
$var wire 1 ] sO $end
$var wire 1 ^ sX $end
$var wire 1 _ out $end
$scope module mux1 $end
$var wire 2 ` S [1:0] $end
$var wire 1 [ a $end
$var wire 1 ] b $end
$var wire 1 ^ c $end
$var wire 1 \ d $end
$var reg 1 _ out $end
$upscope $end
$upscope $end
$scope module cl2 $end
$var wire 2 a S [1:0] $end
$var wire 1 b a $end
$var wire 1 c b $end
$var wire 1 d sA $end
$var wire 1 e sN $end
$var wire 1 f sO $end
$var wire 1 g sX $end
$var wire 1 h out $end
$scope module mux1 $end
$var wire 2 i S [1:0] $end
$var wire 1 d a $end
$var wire 1 f b $end
$var wire 1 g c $end
$var wire 1 e d $end
$var reg 1 h out $end
$upscope $end
$upscope $end
$scope module cl3 $end
$var wire 2 j S [1:0] $end
$var wire 1 k a $end
$var wire 1 l b $end
$var wire 1 m sA $end
$var wire 1 n sN $end
$var wire 1 o sO $end
$var wire 1 p sX $end
$var wire 1 q out $end
$scope module mux1 $end
$var wire 2 r S [1:0] $end
$var wire 1 m a $end
$var wire 1 o b $end
$var wire 1 p c $end
$var wire 1 n d $end
$var reg 1 q out $end
$upscope $end
$upscope $end
$scope module cl4 $end
$var wire 2 s S [1:0] $end
$var wire 1 t a $end
$var wire 1 u b $end
$var wire 1 v sA $end
$var wire 1 w sN $end
$var wire 1 x sO $end
$var wire 1 y sX $end
$var wire 1 z out $end
$scope module mux1 $end
$var wire 2 { S [1:0] $end
$var wire 1 v a $end
$var wire 1 x b $end
$var wire 1 y c $end
$var wire 1 w d $end
$var reg 1 z out $end
$upscope $end
$upscope $end
$upscope $end
$upscope $end
$scope task check $end
$var reg 5 | expected_R [4:0] $end
$var reg 1 } expected_c $end
$var reg 1 ~ expected_s $end
$var reg 1 !" expected_z $end
$upscope $end
$upscope $end
$scope module fa $end
$var wire 1 "" a $end
$var wire 1 #" b $end
$var wire 1 $" c_in $end
$var wire 1 %" sum $end
$var wire 1 &" c_out $end
$upscope $end
$enddefinitions $end
$comment Show the parameter values. $end
$dumpall
$end
#0
$dumpvars
x&"
x%"
z$"
z#"
z""
x!"
x~
x}
bx |
b0 {
0z
0y
0x
1w
0v
0u
0t
b0 s
b0 r
0q
0p
0o
1n
0m
0l
0k
b0 j
b0 i
0h
0g
0f
1e
0d
0c
0b
b0 a
b0 `
0_
0^
0]
1\
0[
0Z
0Y
b0 X
b0 W
b0 V
b0 U
b0 T
b0 S
b0 R
b0 Q
b0 P
b0 O
b0 N
b0 M
b0 L
b1 K
b1 J
b1 I
b0 H
b0 G
b0 F
b0 E
b0 D
b1 C
b0 B
1A
1@
0?
1>
b0 =
b0 <
b0 ;
b0 :
b0 9
b0 8
07
b0 6
b0 5
b0 4
b0 3
b0 2
b0 1
b0 0
b0 /
b0 .
0-
b0 ,
b0 +
b0 *
x)
x(
x'
x&
x%
b0 $
0#
0"
1!
$end
#1
0%
0)
0&
1!"
0'
0(
0~
0}
b0 |
#1000
0!
b1 $
b1 6
b1 8
1]
1^
b1 3
b1 :
b1 S
1Z
b1 4
b1 D
b1 F
b1 R
b1 U
b1 B
b1 G
b1 P
b1 +
b1 0
b1 <
b1 O
#1001
0!"
b1 |
#2000
b10 $
b10 6
b10 8
0]
0^
1f
1g
b10 3
b10 :
b10 S
0Z
1c
b10 4
b10 D
b10 F
b10 R
b10 U
b10 B
b10 G
b10 P
b10 +
b10 0
b10 <
b10 O
#2001
b10 |
#3000
b11 $
b11 6
b11 8
1]
1^
b11 3
b11 :
b11 S
1Z
b11 4
b11 D
b11 F
b11 R
b11 U
b11 B
b11 G
b11 P
b11 +
b11 0
b11 <
b11 O
#3001
b11 |
#4000
b100 $
b100 6
b100 8
0]
0^
0f
0g
1o
1p
b100 3
b100 :
b100 S
0Z
0c
1l
b100 4
b100 D
b100 F
b100 R
b100 U
b100 B
b100 G
b100 P
b100 +
b100 0
b100 <
b100 O
#4001
b100 |
#5000
b101 $
b101 6
b101 8
1]
1^
b101 3
b101 :
b101 S
1Z
b101 4
b101 D
b101 F
b101 R
b101 U
b101 B
b101 G
b101 P
b101 +
b101 0
b101 <
b101 O
#5001
b101 |
#6000
b110 $
b110 6
b110 8
0]
0^
1f
1g
b110 3
b110 :
b110 S
0Z
1c
b110 4
b110 D
b110 F
b110 R
b110 U
b110 B
b110 G
b110 P
b110 +
b110 0
b110 <
b110 O
#6001
b110 |
#7000
b111 $
b111 6
b111 8
1]
1^
b111 3
b111 :
b111 S
1Z
b111 4
b111 D
b111 F
b111 R
b111 U
b111 B
b111 G
b111 P
b111 +
b111 0
b111 <
b111 O
#7001
b111 |
#8000
1"
b1000 $
b1000 6
b1000 8
0]
0^
0f
0g
0o
0p
1x
1y
b1000 3
b1000 :
b1000 S
0Z
0c
0l
1u
b1000 4
b1000 D
b1000 F
b1000 R
b1000 U
b1000 B
b1000 G
b1000 P
b1000 +
b1000 0
b1000 <
b1000 O
#8001
1~
b1000 |
#9000
b1001 $
b1001 6
b1001 8
1]
1^
b1001 3
b1001 :
b1001 S
1Z
b1001 4
b1001 D
b1001 F
b1001 R
b1001 U
b1001 B
b1001 G
b1001 P
b1001 +
b1001 0
b1001 <
b1001 O
#9001
b1001 |
#10000
b1010 $
b1010 6
b1010 8
0]
0^
1f
1g
b1010 3
b1010 :
b1010 S
0Z
1c
b1010 4
b1010 D
b1010 F
b1010 R
b1010 U
b1010 B
b1010 G
b1010 P
b1010 +
b1010 0
b1010 <
b1010 O
#10001
b1010 |
#11000
b1011 $
b1011 6
b1011 8
1]
1^
b1011 3
b1011 :
b1011 S
1Z
b1011 4
b1011 D
b1011 F
b1011 R
b1011 U
b1011 B
b1011 G
b1011 P
b1011 +
b1011 0
b1011 <
b1011 O
#11001
b1011 |
#12000
b1100 $
b1100 6
b1100 8
0]
0^
0f
0g
1o
1p
b1100 3
b1100 :
b1100 S
0Z
0c
1l
b1100 4
b1100 D
b1100 F
b1100 R
b1100 U
b1100 B
b1100 G
b1100 P
b1100 +
b1100 0
b1100 <
b1100 O
#12001
b1100 |
#13000
b1101 $
b1101 6
b1101 8
1]
1^
b1101 3
b1101 :
b1101 S
1Z
b1101 4
b1101 D
b1101 F
b1101 R
b1101 U
b1101 B
b1101 G
b1101 P
b1101 +
b1101 0
b1101 <
b1101 O
#13001
b1101 |
#14000
b1110 $
b1110 6
b1110 8
0]
0^
1f
1g
b1110 3
b1110 :
b1110 S
0Z
1c
b1110 4
b1110 D
b1110 F
b1110 R
b1110 U
b1110 B
b1110 G
b1110 P
b1110 +
b1110 0
b1110 <
b1110 O
#14001
b1110 |
#15000
b1111 $
b1111 6
b1111 8
1]
1^
b1111 3
b1111 :
b1111 S
1Z
b1111 4
b1111 D
b1111 F
b1111 R
b1111 U
b1111 B
b1111 G
b1111 P
b1111 +
b1111 0
b1111 <
b1111 O
#15001
b1111 |
#16000
0"
0f
0g
0o
0p
0x
0y
b1 $
b1 6
b1 8
0\
0Z
0c
0l
0u
b1 3
b1 :
b1 S
1Y
b0 4
b0 D
b0 F
b0 R
b0 U
b1 5
b1 E
b1 M
b1 Q
b1 T
b0 B
b0 G
b0 P
b1 *
b1 /
b1 ;
b1 L
b1 N
b0 +
b0 0
b0 <
b0 O
#16001
0~
b1 |
#17000
b1 2
b1 9
b1 W
1_
b10 $
b10 6
b10 8
1[
0^
b10 3
b10 :
b10 S
1Z
b1 4
b1 D
b1 F
b1 R
b1 U
b1 B
b1 G
b1 P
b1 +
b1 0
b1 <
b1 O
#17001
b10 |
#18000
b0 2
b0 9
b0 W
0_
b11 $
b11 6
b11 8
0[
1^
1f
1g
b11 3
b11 :
b11 S
0Z
1c
b10 4
b10 D
b10 F
b10 R
b10 U
b10 B
b10 G
b10 P
b10 +
b10 0
b10 <
b10 O
#18001
b11 |
#19000
b1 2
b1 9
b1 W
1_
b100 $
b100 6
b100 8
1[
0^
b100 3
b100 :
b100 S
1Z
b11 4
b11 D
b11 F
b11 R
b11 U
b11 B
b11 G
b11 P
b11 +
b11 0
b11 <
b11 O
#19001
b100 |
#20000
b0 2
b0 9
b0 W
0_
b101 $
b101 6
b101 8
0[
1^
0f
0g
1o
1p
b101 3
b101 :
b101 S
0Z
0c
1l
b100 4
b100 D
b100 F
b100 R
b100 U
b100 B
b100 G
b100 P
b100 +
b100 0
b100 <
b100 O
#20001
b101 |
#21000
b1 2
b1 9
b1 W
1_
b110 $
b110 6
b110 8
1[
0^
b110 3
b110 :
b110 S
1Z
b101 4
b101 D
b101 F
b101 R
b101 U
b101 B
b101 G
b101 P
b101 +
b101 0
b101 <
b101 O
#21001
b110 |
#22000
b0 2
b0 9
b0 W
0_
b111 $
b111 6
b111 8
0[
1^
1f
1g
b111 3
b111 :
b111 S
0Z
1c
b110 4
b110 D
b110 F
b110 R
b110 U
b110 B
b110 G
b110 P
b110 +
b110 0
b110 <
b110 O
#22001
b111 |
#23000
1"
b1 2
b1 9
b1 W
1_
b1000 $
b1000 6
b1000 8
1[
0^
b1000 3
b1000 :
b1000 S
1Z
b111 4
b111 D
b111 F
b111 R
b111 U
b111 B
b111 G
b111 P
b111 +
b111 0
b111 <
b111 O
#23001
1~
b1000 |
#24000
b0 2
b0 9
b0 W
0_
b1001 $
b1001 6
b1001 8
0[
1^
0f
0g
0o
0p
1x
1y
b1001 3
b1001 :
b1001 S
0Z
0c
0l
1u
b1000 4
b1000 D
b1000 F
b1000 R
b1000 U
b1000 B
b1000 G
b1000 P
b1000 +
b1000 0
b1000 <
b1000 O
#24001
b1001 |
#25000
b1 2
b1 9
b1 W
1_
b1010 $
b1010 6
b1010 8
1[
0^
b1010 3
b1010 :
b1010 S
1Z
b1001 4
b1001 D
b1001 F
b1001 R
b1001 U
b1001 B
b1001 G
b1001 P
b1001 +
b1001 0
b1001 <
b1001 O
#25001
b1010 |
#26000
b0 2
b0 9
b0 W
0_
b1011 $
b1011 6
b1011 8
0[
1^
1f
1g
b1011 3
b1011 :
b1011 S
0Z
1c
b1010 4
b1010 D
b1010 F
b1010 R
b1010 U
b1010 B
b1010 G
b1010 P
b1010 +
b1010 0
b1010 <
b1010 O
#26001
b1011 |
#27000
b1 2
b1 9
b1 W
1_
b1100 $
b1100 6
b1100 8
1[
0^
b1100 3
b1100 :
b1100 S
1Z
b1011 4
b1011 D
b1011 F
b1011 R
b1011 U
b1011 B
b1011 G
b1011 P
b1011 +
b1011 0
b1011 <
b1011 O
#27001
b1100 |
#28000
b0 2
b0 9
b0 W
0_
b1101 $
b1101 6
b1101 8
0[
1^
0f
0g
1o
1p
b1101 3
b1101 :
b1101 S
0Z
0c
1l
b1100 4
b1100 D
b1100 F
b1100 R
b1100 U
b1100 B
b1100 G
b1100 P
b1100 +
b1100 0
b1100 <
b1100 O
#28001
b1101 |
#29000
b1 2
b1 9
b1 W
1_
b1110 $
b1110 6
b1110 8
1[
0^
b1110 3
b1110 :
b1110 S
1Z
b1101 4
b1101 D
b1101 F
b1101 R
b1101 U
b1101 B
b1101 G
b1101 P
b1101 +
b1101 0
b1101 <
b1101 O
#29001
b1110 |
#30000
b0 2
b0 9
b0 W
0_
b1111 $
b1111 6
b1111 8
0[
1^
1f
1g
b1111 3
b1111 :
b1111 S
0Z
1c
b1110 4
b1110 D
b1110 F
b1110 R
b1110 U
b1110 B
b1110 G
b1110 P
b1110 +
b1110 0
b1110 <
b1110 O
#30001
b1111 |
#31000
0"
1!
b1 2
b1 9
b1 W
1_
b0 $
b0 6
b0 8
1[
0^
b0 3
b0 :
b0 S
1#
1Z
b1111 4
b1111 D
b1111 F
b1111 R
b1111 U
b1111 B
b1111 G
b1111 P
b1111 +
b1111 0
b1111 <
b1111 O
#31001
1!"
0~
1}
b10000 |
#32000
0!
b0 2
b0 9
b0 W
0_
0o
0p
0x
0y
b10 $
b10 6
b10 8
0[
0]
1\
0e
0#
0Z
0c
0l
0u
b10 3
b10 :
b10 S
0Y
1b
b0 4
b0 D
b0 F
b0 R
b0 U
b10 5
b10 E
b10 M
b10 Q
b10 T
b0 B
b0 G
b0 P
b10 *
b10 /
b10 ;
b10 L
b10 N
b0 +
b0 0
b0 <
b0 O
#32001
0!"
0}
b10 |
#33000
b11 $
b11 6
b11 8
1]
1^
b11 3
b11 :
b11 S
1Z
b1 4
b1 D
b1 F
b1 R
b1 U
b1 B
b1 G
b1 P
b1 +
b1 0
b1 <
b1 O
#33001
b11 |
#34000
b10 2
b10 9
b10 W
1h
b100 $
b100 6
b100 8
0]
0^
1d
0g
b100 3
b100 :
b100 S
0Z
1c
b10 4
b10 D
b10 F
b10 R
b10 U
b10 B
b10 G
b10 P
b10 +
b10 0
b10 <
b10 O
#34001
b100 |
#35000
b101 $
b101 6
b101 8
1]
1^
b101 3
b101 :
b101 S
1Z
b11 4
b11 D
b11 F
b11 R
b11 U
b11 B
b11 G
b11 P
b11 +
b11 0
b11 <
b11 O
#35001
b101 |
#36000
b0 2
b0 9
b0 W
0h
b110 $
b110 6
b110 8
0]
0^
0d
1g
1o
1p
b110 3
b110 :
b110 S
0Z
0c
1l
b100 4
b100 D
b100 F
b100 R
b100 U
b100 B
b100 G
b100 P
b100 +
b100 0
b100 <
b100 O
#36001
b110 |
#37000
b111 $
b111 6
b111 8
1]
1^
b111 3
b111 :
b111 S
1Z
b101 4
b101 D
b101 F
b101 R
b101 U
b101 B
b101 G
b101 P
b101 +
b101 0
b101 <
b101 O
#37001
b111 |
#38000
1"
b10 2
b10 9
b10 W
1h
b1000 $
b1000 6
b1000 8
0]
0^
1d
0g
b1000 3
b1000 :
b1000 S
0Z
1c
b110 4
b110 D
b110 F
b110 R
b110 U
b110 B
b110 G
b110 P
b110 +
b110 0
b110 <
b110 O
#38001
1~
b1000 |
#39000
b1001 $
b1001 6
b1001 8
1]
1^
b1001 3
b1001 :
b1001 S
1Z
b111 4
b111 D
b111 F
b111 R
b111 U
b111 B
b111 G
b111 P
b111 +
b111 0
b111 <
b111 O
#39001
b1001 |
#40000
b0 2
b0 9
b0 W
0h
b1010 $
b1010 6
b1010 8
0]
0^
0d
1g
0o
0p
1x
1y
b1010 3
b1010 :
b1010 S
0Z
0c
0l
1u
b1000 4
b1000 D
b1000 F
b1000 R
b1000 U
b1000 B
b1000 G
b1000 P
b1000 +
b1000 0
b1000 <
b1000 O
#40001
b1010 |
#41000
b1011 $
b1011 6
b1011 8
1]
1^
b1011 3
b1011 :
b1011 S
1Z
b1001 4
b1001 D
b1001 F
b1001 R
b1001 U
b1001 B
b1001 G
b1001 P
b1001 +
b1001 0
b1001 <
b1001 O
#41001
b1011 |
#42000
b10 2
b10 9
b10 W
1h
b1100 $
b1100 6
b1100 8
0]
0^
1d
0g
b1100 3
b1100 :
b1100 S
0Z
1c
b1010 4
b1010 D
b1010 F
b1010 R
b1010 U
b1010 B
b1010 G
b1010 P
b1010 +
b1010 0
b1010 <
b1010 O
#42001
b1100 |
#43000
b1101 $
b1101 6
b1101 8
1]
1^
b1101 3
b1101 :
b1101 S
1Z
b1011 4
b1011 D
b1011 F
b1011 R
b1011 U
b1011 B
b1011 G
b1011 P
b1011 +
b1011 0
b1011 <
b1011 O
#43001
b1101 |
#44000
b0 2
b0 9
b0 W
0h
b1110 $
b1110 6
b1110 8
0]
0^
0d
1g
1o
1p
b1110 3
b1110 :
b1110 S
0Z
0c
1l
b1100 4
b1100 D
b1100 F
b1100 R
b1100 U
b1100 B
b1100 G
b1100 P
b1100 +
b1100 0
b1100 <
b1100 O
#44001
b1110 |
#45000
b1111 $
b1111 6
b1111 8
1]
1^
b1111 3
b1111 :
b1111 S
1Z
b1101 4
b1101 D
b1101 F
b1101 R
b1101 U
b1101 B
b1101 G
b1101 P
b1101 +
b1101 0
b1101 <
b1101 O
#45001
b1111 |
#46000
0"
1!
b10 2
b10 9
b10 W
1h
b0 $
b0 6
b0 8
0]
0^
1d
0g
b0 3
b0 :
b0 S
1#
0Z
1c
b1110 4
b1110 D
b1110 F
b1110 R
b1110 U
b1110 B
b1110 G
b1110 P
b1110 +
b1110 0
b1110 <
b1110 O
#46001
1!"
0~
1}
b10000 |
#47000
0!
b1 $
b1 6
b1 8
1]
1^
b1 3
b1 :
b1 S
1Z
b1111 4
b1111 D
b1111 F
b1111 R
b1111 U
b1111 B
b1111 G
b1111 P
b1111 +
b1111 0
b1111 <
b1111 O
#47001
0!"
b10001 |
#48000
b0 2
b0 9
b0 W
0h
0d
1g
0o
0p
0x
0y
b11 $
b11 6
b11 8
0\
0#
0Z
0c
0l
0u
b11 3
b11 :
b11 S
1Y
b0 4
b0 D
b0 F
b0 R
b0 U
b11 5
b11 E
b11 M
b11 Q
b11 T
b0 B
b0 G
b0 P
b11 *
b11 /
b11 ;
b11 L
b11 N
b0 +
b0 0
b0 <
b0 O
#48001
0}
b11 |
#49000
b1 2
b1 9
b1 W
1_
b100 $
b100 6
b100 8
1[
0^
b100 3
b100 :
b100 S
1Z
b1 4
b1 D
b1 F
b1 R
b1 U
b1 B
b1 G
b1 P
b1 +
b1 0
b1 <
b1 O
#49001
b100 |
#50000
0_
b10 2
b10 9
b10 W
1h
b101 $
b101 6
b101 8
0[
1^
1d
0g
b101 3
b101 :
b101 S
0Z
1c
b10 4
b10 D
b10 F
b10 R
b10 U
b10 B
b10 G
b10 P
b10 +
b10 0
b10 <
b10 O
#50001
b101 |
#51000
b11 2
b11 9
b11 W
1_
b110 $
b110 6
b110 8
1[
0^
b110 3
b110 :
b110 S
1Z
b11 4
b11 D
b11 F
b11 R
b11 U
b11 B
b11 G
b11 P
b11 +
b11 0
b11 <
b11 O
#51001
b110 |
#52000
0_
b0 2
b0 9
b0 W
0h
b111 $
b111 6
b111 8
0[
1^
0d
1g
1o
1p
b111 3
b111 :
b111 S
0Z
0c
1l
b100 4
b100 D
b100 F
b100 R
b100 U
b100 B
b100 G
b100 P
b100 +
b100 0
b100 <
b100 O
#52001
b111 |
#53000
1"
b1 2
b1 9
b1 W
1_
b1000 $
b1000 6
b1000 8
1[
0^
b1000 3
b1000 :
b1000 S
1Z
b101 4
b101 D
b101 F
b101 R
b101 U
b101 B
b101 G
b101 P
b101 +
b101 0
b101 <
b101 O
#53001
1~
b1000 |
#54000
0_
b10 2
b10 9
b10 W
1h
b1001 $
b1001 6
b1001 8
0[
1^
1d
0g
b1001 3
b1001 :
b1001 S
0Z
1c
b110 4
b110 D
b110 F
b110 R
b110 U
b110 B
b110 G
b110 P
b110 +
b110 0
b110 <
b110 O
#54001
b1001 |
#55000
b11 2
b11 9
b11 W
1_
b1010 $
b1010 6
b1010 8
1[
0^
b1010 3
b1010 :
b1010 S
1Z
b111 4
b111 D
b111 F
b111 R
b111 U
b111 B
b111 G
b111 P
b111 +
b111 0
b111 <
b111 O
#55001
b1010 |
#56000
0_
b0 2
b0 9
b0 W
0h
b1011 $
b1011 6
b1011 8
0[
1^
0d
1g
0o
0p
1x
1y
b1011 3
b1011 :
b1011 S
0Z
0c
0l
1u
b1000 4
b1000 D
b1000 F
b1000 R
b1000 U
b1000 B
b1000 G
b1000 P
b1000 +
b1000 0
b1000 <
b1000 O
#56001
b1011 |
#57000
b1 2
b1 9
b1 W
1_
b1100 $
b1100 6
b1100 8
1[
0^
b1100 3
b1100 :
b1100 S
1Z
b1001 4
b1001 D
b1001 F
b1001 R
b1001 U
b1001 B
b1001 G
b1001 P
b1001 +
b1001 0
b1001 <
b1001 O
#57001
b1100 |
